fastsk/__init__.py
fastsk/_fastsk.cpython-37m-darwin.so
fastsk/old_utils.py
fastsk/utils.py
fastsk-0.0.2.dist-info/LICENSE
fastsk-0.0.2.dist-info/METADATA
fastsk-0.0.2.dist-info/WHEEL
fastsk-0.0.2.dist-info/top_level.txt
fastsk-0.0.2.dist-info/RECORD
